crack/__init__.py
crack/font.py
crack/run.py
crack/util.py
crack-0.7.dist-info/LICENSE
crack-0.7.dist-info/METADATA
crack-0.7.dist-info/WHEEL
crack-0.7.dist-info/entry_points.txt
crack-0.7.dist-info/top_level.txt
crack-0.7.dist-info/RECORD
