Metadata-Version: 2.1
Name: crack
Version: 0.7
Summary: Crack tools all here!
Home-page: https://leesoar.com/explore
Author: leesoar
Author-email: core@111.com
License: MIT
Keywords: crack,base64,exploit,rsa,aes,md5,oct,font
Platform: UNKNOWN
Classifier: License :: OSI Approved :: MIT License
Classifier: Programming Language :: Python :: 3.5
Classifier: Programming Language :: Python :: 3.6
Classifier: Programming Language :: Python :: 3.7
Classifier: Programming Language :: Python :: Implementation :: CPython
Classifier: Programming Language :: Python :: Implementation :: PyPy
Requires-Python: >=3.3.0
Requires-Dist: fontTools
Requires-Dist: requests
Requires-Dist: pycryptodome
Requires-Dist: pysodium
